<?xml version='1.0' encoding='utf-8'?> 
<!-- Quest 704: Miss Queen -->
<list upgradeList="true">
   
   <item id="1">
   <ingredient id="11974" count="10" enchant="0"/>
   <ingredient id="28228" count="1" enchant="0"/>
   <ingredient id="26123" count="1" enchant="0"/>
   <ingredient id="28218" count="1" enchant="0"/>
   <ingredient id="28223" count="1" enchant="0"/>   
   <production id="26112" count="1" enchant="0"/>
   <production id="26227" count="1" enchant="0"/> 
   <production id="26217" count="1" enchant="0"/> 
   <production id="26222" count="1" enchant="0"/>       
   </item> 
   <item id="2">
   <ingredient id="11974" count="10" enchant="0"/>
   <ingredient id="28229" count="1" enchant="0"/>
   <ingredient id="26124" count="1" enchant="0"/>
   <ingredient id="28219" count="1" enchant="0"/>
   <ingredient id="28224" count="1" enchant="0"/>   
   <production id="26112" count="1" enchant="0"/>
   <production id="26227" count="1" enchant="0"/> 
   <production id="26217" count="1" enchant="0"/> 
   <production id="26222" count="1" enchant="0"/>   
   </item>
   <item id="3">
   <ingredient id="11974" count="10" enchant="0"/>
   <ingredient id="9666" count="1" enchant="0"/>
   <ingredient id="9657" count="1" enchant="0"/>
   <ingredient id="9658" count="1" enchant="0"/>
   <ingredient id="9659" count="1" enchant="0"/>
   <ingredient id="9660" count="1" enchant="0"/>   
   <production id="26112" count="1" enchant="0"/>
   <production id="26227" count="1" enchant="0"/> 
   <production id="26217" count="1" enchant="0"/> 
   <production id="26222" count="1" enchant="0"/>   
   </item>
   <item id="4">
   <ingredient id="11974" count="10" enchant="0"/>
   <ingredient id="9665" count="1" enchant="0"/>
   <ingredient id="9661" count="1" enchant="0"/>
   <ingredient id="9662" count="1" enchant="0"/>
   <ingredient id="9663" count="1" enchant="0"/>
   <ingredient id="9664" count="1" enchant="0"/>   
   <production id="26112" count="1" enchant="0"/>
   <production id="26227" count="1" enchant="0"/> 
   <production id="26217" count="1" enchant="0"/> 
   <production id="26222" count="1" enchant="0"/>  
   </item>
   <item id="5">
   <ingredient id="11974" count="10" enchant="0"/>
   <ingredient id="17180" count="1" enchant="0"/>
   <ingredient id="17134" count="1" enchant="0"/>
   <ingredient id="17135" count="1" enchant="0"/>
   <ingredient id="17136" count="1" enchant="0"/>
   <ingredient id="17137" count="1" enchant="0"/>   
   <production id="26112" count="1" enchant="0"/>
   <production id="26227" count="1" enchant="0"/> 
   <production id="26217" count="1" enchant="0"/> 
   <production id="26222" count="1" enchant="0"/> 
   </item>
   <item id="6">
   <ingredient id="11974" count="10" enchant="0"/>
   <ingredient id="17182" count="1" enchant="0"/>
   <ingredient id="17144" count="1" enchant="0"/>
   <ingredient id="17145" count="1" enchant="0"/>
   <ingredient id="17146" count="1" enchant="0"/>
   <ingredient id="17147" count="1" enchant="0"/>   
   <production id="26112" count="1" enchant="0"/>
   <production id="26227" count="1" enchant="0"/> 
   <production id="26217" count="1" enchant="0"/> 
   <production id="26222" count="1" enchant="0"/>    
   </item>
   <item id="7">
   <ingredient id="11974" count="10" enchant="0"/>
   <ingredient id="17167" count="1" enchant="0"/>
   <ingredient id="17168" count="1" enchant="0"/>
   <ingredient id="17169" count="1" enchant="0"/>
   <ingredient id="17170" count="1" enchant="0"/>
   <ingredient id="17171" count="1" enchant="0"/>   
   <production id="26112" count="1" enchant="0"/>
   <production id="26227" count="1" enchant="0"/> 
   <production id="26217" count="1" enchant="0"/> 
   <production id="26222" count="1" enchant="0"/>  
   </item>
   <item id="8">
   <ingredient id="11974" count="10" enchant="0"/>
   <ingredient id="17172" count="1" enchant="0"/>
   <ingredient id="17173" count="1" enchant="0"/>
   <ingredient id="17174" count="1" enchant="0"/>
   <ingredient id="17175" count="1" enchant="0"/>  
   <production id="26112" count="1" enchant="0"/>
   <production id="26227" count="1" enchant="0"/> 
   <production id="26217" count="1" enchant="0"/> 
   <production id="26222" count="1" enchant="0"/>    
   </item>
      <item id="9">
	  <ingredient id="11974" count="10" enchant="0"/>
   <ingredient id="17176" count="1" enchant="0"/>
   <ingredient id="17177" count="1" enchant="0"/>
   <ingredient id="17178" count="1" enchant="0"/>
   <ingredient id="17179" count="1" enchant="0"/>  
   <production id="26112" count="1" enchant="0"/>
   <production id="26227" count="1" enchant="0"/> 
   <production id="26217" count="1" enchant="0"/> 
   <production id="26222" count="1" enchant="0"/>  
   </item> 
   <item id="10">
   <ingredient id="11974" count="10" enchant="0"/>
   <ingredient id="16500" count="1" enchant="0"/>
   <ingredient id="16502" count="1" enchant="0"/>
   <ingredient id="16504" count="1" enchant="0"/>
   <ingredient id="16506" count="1" enchant="0"/>
   <ingredient id="16508" count="1" enchant="0"/>   
   <production id="26112" count="1" enchant="0"/>
   <production id="26227" count="1" enchant="0"/> 
   <production id="26217" count="1" enchant="0"/> 
   <production id="26222" count="1" enchant="0"/>  
   </item>
      <item id="11">
	  <ingredient id="11974" count="10" enchant="0"/>
   <ingredient id="26122" count="1" enchant="0"/>
   <ingredient id="28227" count="1" enchant="0"/>
   <ingredient id="28217" count="1" enchant="0"/>
   <ingredient id="28222" count="1" enchant="0"/>
 
   <production id="26112" count="1" enchant="0"/>
   <production id="26227" count="1" enchant="0"/> 
   <production id="26217" count="1" enchant="0"/> 
   <production id="26222" count="1" enchant="0"/>   
   </item>
      <item id="12">
	  <ingredient id="11974" count="10" enchant="0"/>
   <ingredient id="28228" count="1" enchant="0"/>
   <ingredient id="26123" count="1" enchant="0"/>
   <ingredient id="28218" count="1" enchant="0"/>
   <ingredient id="28223" count="1" enchant="0"/>   
   <production id="26228" count="1" enchant="0"/>
   <production id="26113" count="1" enchant="0"/>
   <production id="26218" count="1" enchant="0"/>
   <production id="26223" count="1" enchant="0"/>       
   </item> 
   <item id="13">
   <ingredient id="11974" count="10" enchant="0"/>
   <ingredient id="28229" count="1" enchant="0"/>
   <ingredient id="26124" count="1" enchant="0"/>
   <ingredient id="28219" count="1" enchant="0"/>
   <ingredient id="28224" count="1" enchant="0"/>   
   <production id="26228" count="1" enchant="0"/>
   <production id="26113" count="1" enchant="0"/>
   <production id="26218" count="1" enchant="0"/>
   <production id="26223" count="1" enchant="0"/>   
   </item>
   <item id="14">
   <ingredient id="11974" count="10" enchant="0"/>
   <ingredient id="9666" count="1" enchant="0"/>
   <ingredient id="9657" count="1" enchant="0"/>
   <ingredient id="9658" count="1" enchant="0"/>
   <ingredient id="9659" count="1" enchant="0"/>
   <ingredient id="9660" count="1" enchant="0"/>   
   <production id="26228" count="1" enchant="0"/>
   <production id="26113" count="1" enchant="0"/>
   <production id="26218" count="1" enchant="0"/>
   <production id="26223" count="1" enchant="0"/>   
   </item>
   <item id="15">
   <ingredient id="11974" count="10" enchant="0"/>
   <ingredient id="9665" count="1" enchant="0"/>
   <ingredient id="9661" count="1" enchant="0"/>
   <ingredient id="9662" count="1" enchant="0"/>
   <ingredient id="9663" count="1" enchant="0"/>
   <ingredient id="9664" count="1" enchant="0"/>   
   <production id="26228" count="1" enchant="0"/>
   <production id="26113" count="1" enchant="0"/>
   <production id="26218" count="1" enchant="0"/>
   <production id="26223" count="1" enchant="0"/> 
   </item>
   <item id="16">
   <ingredient id="11974" count="10" enchant="0"/>
   <ingredient id="17180" count="1" enchant="0"/>
   <ingredient id="17134" count="1" enchant="0"/>
   <ingredient id="17135" count="1" enchant="0"/>
   <ingredient id="17136" count="1" enchant="0"/>
   <ingredient id="17137" count="1" enchant="0"/>   
   <production id="26228" count="1" enchant="0"/>
   <production id="26113" count="1" enchant="0"/>
   <production id="26218" count="1" enchant="0"/>
   <production id="26223" count="1" enchant="0"/> 
   </item>
   <item id="17">
   <ingredient id="11974" count="10" enchant="0"/>
   <ingredient id="17182" count="1" enchant="0"/>
   <ingredient id="17144" count="1" enchant="0"/>
   <ingredient id="17145" count="1" enchant="0"/>
   <ingredient id="17146" count="1" enchant="0"/>
   <ingredient id="17147" count="1" enchant="0"/>   
   <production id="26228" count="1" enchant="0"/>
   <production id="26113" count="1" enchant="0"/>
   <production id="26218" count="1" enchant="0"/>
   <production id="26223" count="1" enchant="0"/>    
   </item>
   <item id="18">
   <ingredient id="11974" count="10" enchant="0"/>
   <ingredient id="17167" count="1" enchant="0"/>
   <ingredient id="17168" count="1" enchant="0"/>
   <ingredient id="17169" count="1" enchant="0"/>
   <ingredient id="17170" count="1" enchant="0"/>
   <ingredient id="17171" count="1" enchant="0"/>   
   <production id="26228" count="1" enchant="0"/>
   <production id="26113" count="1" enchant="0"/>
   <production id="26218" count="1" enchant="0"/>
   <production id="26223" count="1" enchant="0"/>  
   </item>
   <item id="19">
   <ingredient id="11974" count="10" enchant="0"/>
   <ingredient id="17172" count="1" enchant="0"/>
   <ingredient id="17173" count="1" enchant="0"/>
   <ingredient id="17174" count="1" enchant="0"/>
   <ingredient id="17175" count="1" enchant="0"/>  
   <production id="26228" count="1" enchant="0"/>
   <production id="26113" count="1" enchant="0"/>
   <production id="26218" count="1" enchant="0"/>
   <production id="26223" count="1" enchant="0"/>    
   </item>
      <item id="20">
	  <ingredient id="11974" count="10" enchant="0"/>
   <ingredient id="17176" count="1" enchant="0"/>
   <ingredient id="17177" count="1" enchant="0"/>
   <ingredient id="17178" count="1" enchant="0"/>
   <ingredient id="17179" count="1" enchant="0"/>  
   <production id="26228" count="1" enchant="0"/>
   <production id="26113" count="1" enchant="0"/>
   <production id="26218" count="1" enchant="0"/>
   <production id="26223" count="1" enchant="0"/>  
   </item> 
   <item id="21">
   <ingredient id="11974" count="10" enchant="0"/>
   <ingredient id="16500" count="1" enchant="0"/>
   <ingredient id="16502" count="1" enchant="0"/>
   <ingredient id="16504" count="1" enchant="0"/>
   <ingredient id="16506" count="1" enchant="0"/>
   <ingredient id="16508" count="1" enchant="0"/>   
   <production id="26228" count="1" enchant="0"/>
   <production id="26113" count="1" enchant="0"/>
   <production id="26218" count="1" enchant="0"/>
   <production id="26223" count="1" enchant="0"/>  
   </item>
      <item id="22">
	  <ingredient id="11974" count="10" enchant="0"/>
   <ingredient id="26122" count="1" enchant="0"/>
   <ingredient id="28227" count="1" enchant="0"/>
   <ingredient id="28217" count="1" enchant="0"/>
   <ingredient id="28222" count="1" enchant="0"/>
 
   <production id="26228" count="1" enchant="0"/>
   <production id="26113" count="1" enchant="0"/>
   <production id="26218" count="1" enchant="0"/>
   <production id="26223" count="1" enchant="0"/>  
   </item>
      <item id="23">
	  <ingredient id="11974" count="10" enchant="0"/>
   <ingredient id="28228" count="1" enchant="0"/>
   <ingredient id="26123" count="1" enchant="0"/>
   <ingredient id="28218" count="1" enchant="0"/>
   <ingredient id="28223" count="1" enchant="0"/>   
   <production id="26229" count="1" enchant="0"/>
   <production id="26114" count="1" enchant="0"/>
   <production id="26219" count="1" enchant="0"/>
   <production id="26224" count="1" enchant="0"/>        
   </item> 
   <item id="24">
   <ingredient id="11974" count="10" enchant="0"/>
   <ingredient id="28229" count="1" enchant="0"/>
   <ingredient id="26124" count="1" enchant="0"/>
   <ingredient id="28219" count="1" enchant="0"/>
   <ingredient id="28224" count="1" enchant="0"/>   
   <production id="26229" count="1" enchant="0"/>
   <production id="26114" count="1" enchant="0"/>
   <production id="26219" count="1" enchant="0"/>
   <production id="26224" count="1" enchant="0"/>   
   </item>
   <item id="25">
   <ingredient id="11974" count="10" enchant="0"/>
   <ingredient id="9666" count="1" enchant="0"/>
   <ingredient id="9657" count="1" enchant="0"/>
   <ingredient id="9658" count="1" enchant="0"/>
   <ingredient id="9659" count="1" enchant="0"/>
   <ingredient id="9660" count="1" enchant="0"/>   
   <production id="26229" count="1" enchant="0"/>
   <production id="26114" count="1" enchant="0"/>
   <production id="26219" count="1" enchant="0"/>
   <production id="26224" count="1" enchant="0"/>   
   </item>
   <item id="26">
   <ingredient id="11974" count="10" enchant="0"/>
   <ingredient id="9665" count="1" enchant="0"/>
   <ingredient id="9661" count="1" enchant="0"/>
   <ingredient id="9662" count="1" enchant="0"/>
   <ingredient id="9663" count="1" enchant="0"/>
   <ingredient id="9664" count="1" enchant="0"/>   
   <production id="26229" count="1" enchant="0"/>
   <production id="26114" count="1" enchant="0"/>
   <production id="26219" count="1" enchant="0"/>
   <production id="26224" count="1" enchant="0"/>  
   </item>
   <item id="27">
   <ingredient id="11974" count="10" enchant="0"/>
   <ingredient id="17180" count="1" enchant="0"/>
   <ingredient id="17134" count="1" enchant="0"/>
   <ingredient id="17135" count="1" enchant="0"/>
   <ingredient id="17136" count="1" enchant="0"/>
   <ingredient id="17137" count="1" enchant="0"/>   
   <production id="26229" count="1" enchant="0"/>
   <production id="26114" count="1" enchant="0"/>
   <production id="26219" count="1" enchant="0"/>
   <production id="26224" count="1" enchant="0"/> 
   </item>
   <item id="28">
   <ingredient id="11974" count="10" enchant="0"/>
   <ingredient id="17182" count="1" enchant="0"/>
   <ingredient id="17144" count="1" enchant="0"/>
   <ingredient id="17145" count="1" enchant="0"/>
   <ingredient id="17146" count="1" enchant="0"/>
   <ingredient id="17147" count="1" enchant="0"/>   
   <production id="26229" count="1" enchant="0"/>
   <production id="26114" count="1" enchant="0"/>
   <production id="26219" count="1" enchant="0"/>
   <production id="26224" count="1" enchant="0"/>     
   </item>
   <item id="29">
   <ingredient id="11974" count="10" enchant="0"/>
   <ingredient id="17167" count="1" enchant="0"/>
   <ingredient id="17168" count="1" enchant="0"/>
   <ingredient id="17169" count="1" enchant="0"/>
   <ingredient id="17170" count="1" enchant="0"/>
   <ingredient id="17171" count="1" enchant="0"/>   
   <production id="26229" count="1" enchant="0"/>
   <production id="26114" count="1" enchant="0"/>
   <production id="26219" count="1" enchant="0"/>
   <production id="26224" count="1" enchant="0"/>   
   </item>
   <item id="30">
   <ingredient id="11974" count="10" enchant="0"/>
   <ingredient id="17172" count="1" enchant="0"/>
   <ingredient id="17173" count="1" enchant="0"/>
   <ingredient id="17174" count="1" enchant="0"/>
   <ingredient id="17175" count="1" enchant="0"/>  
   <production id="26229" count="1" enchant="0"/>
   <production id="26114" count="1" enchant="0"/>
   <production id="26219" count="1" enchant="0"/>
   <production id="26224" count="1" enchant="0"/>     
   </item>
      <item id="31">
	  <ingredient id="11974" count="10" enchant="0"/>
   <ingredient id="17176" count="1" enchant="0"/>
   <ingredient id="17177" count="1" enchant="0"/>
   <ingredient id="17178" count="1" enchant="0"/>
   <ingredient id="17179" count="1" enchant="0"/>  
   <production id="26229" count="1" enchant="0"/>
   <production id="26114" count="1" enchant="0"/>
   <production id="26219" count="1" enchant="0"/>
   <production id="26224" count="1" enchant="0"/>  
   </item> 
   <item id="32">
   <ingredient id="11974" count="10" enchant="0"/>
   <ingredient id="16500" count="1" enchant="0"/>
   <ingredient id="16502" count="1" enchant="0"/>
   <ingredient id="16504" count="1" enchant="0"/>
   <ingredient id="16506" count="1" enchant="0"/>
   <ingredient id="16508" count="1" enchant="0"/>   
   <production id="26229" count="1" enchant="0"/>
   <production id="26114" count="1" enchant="0"/>
   <production id="26219" count="1" enchant="0"/>
   <production id="26224" count="1" enchant="0"/>   
   </item>
      <item id="33">
	  <ingredient id="11974" count="10" enchant="0"/>
   <ingredient id="26122" count="1" enchant="0"/>
   <ingredient id="28227" count="1" enchant="0"/>
   <ingredient id="28217" count="1" enchant="0"/>
   <ingredient id="28222" count="1" enchant="0"/>
 
   <production id="26229" count="1" enchant="0"/>
   <production id="26114" count="1" enchant="0"/>
   <production id="26219" count="1" enchant="0"/>
   <production id="26224" count="1" enchant="0"/>  
   </item>
      <item id="34">
	  <ingredient id="11974" count="10" enchant="0"/>
   <ingredient id="28228" count="1" enchant="0"/>
   <ingredient id="26123" count="1" enchant="0"/>
   <ingredient id="28218" count="1" enchant="0"/>
   <ingredient id="28223" count="1" enchant="0"/>   
   <production id="9656" count="1" enchant="0"/>
   <production id="9646" count="1" enchant="0"/>
   <production id="9647" count="1" enchant="0"/>
   <production id="9648" count="1" enchant="0"/>
   <production id="9649" count="1" enchant="0"/>         
   </item> 
   <item id="35">
   <ingredient id="11974" count="10" enchant="0"/>
   <ingredient id="28229" count="1" enchant="0"/>
   <ingredient id="26124" count="1" enchant="0"/>
   <ingredient id="28219" count="1" enchant="0"/>
   <ingredient id="28224" count="1" enchant="0"/>   
   <production id="9656" count="1" enchant="0"/>
   <production id="9646" count="1" enchant="0"/>
   <production id="9647" count="1" enchant="0"/>
   <production id="9648" count="1" enchant="0"/>
   <production id="9649" count="1" enchant="0"/>    
   </item>
   <item id="36">
   <ingredient id="11974" count="10" enchant="0"/>
   <ingredient id="9666" count="1" enchant="0"/>
   <ingredient id="9657" count="1" enchant="0"/>
   <ingredient id="9658" count="1" enchant="0"/>
   <ingredient id="9659" count="1" enchant="0"/>
   <ingredient id="9660" count="1" enchant="0"/>   
   <production id="9656" count="1" enchant="0"/>
   <production id="9646" count="1" enchant="0"/>
   <production id="9647" count="1" enchant="0"/>
   <production id="9648" count="1" enchant="0"/>
   <production id="9649" count="1" enchant="0"/>    
   </item>
   <item id="37">
   <ingredient id="11974" count="10" enchant="0"/>
   <ingredient id="9665" count="1" enchant="0"/>
   <ingredient id="9661" count="1" enchant="0"/>
   <ingredient id="9662" count="1" enchant="0"/>
   <ingredient id="9663" count="1" enchant="0"/>
   <ingredient id="9664" count="1" enchant="0"/>   
   <production id="9656" count="1" enchant="0"/>
   <production id="9646" count="1" enchant="0"/>
   <production id="9647" count="1" enchant="0"/>
   <production id="9648" count="1" enchant="0"/>
   <production id="9649" count="1" enchant="0"/>   
   </item>
   <item id="38">
   <ingredient id="11974" count="10" enchant="0"/>
   <ingredient id="17180" count="1" enchant="0"/>
   <ingredient id="17134" count="1" enchant="0"/>
   <ingredient id="17135" count="1" enchant="0"/>
   <ingredient id="17136" count="1" enchant="0"/>
   <ingredient id="17137" count="1" enchant="0"/>   
   <production id="9656" count="1" enchant="0"/>
   <production id="9646" count="1" enchant="0"/>
   <production id="9647" count="1" enchant="0"/>
   <production id="9648" count="1" enchant="0"/>
   <production id="9649" count="1" enchant="0"/> 
   </item>
   <item id="39">
   <ingredient id="11974" count="10" enchant="0"/>
   <ingredient id="17182" count="1" enchant="0"/>
   <ingredient id="17144" count="1" enchant="0"/>
   <ingredient id="17145" count="1" enchant="0"/>
   <ingredient id="17146" count="1" enchant="0"/>
   <ingredient id="17147" count="1" enchant="0"/>   
   <production id="9656" count="1" enchant="0"/>
   <production id="9646" count="1" enchant="0"/>
   <production id="9647" count="1" enchant="0"/>
   <production id="9648" count="1" enchant="0"/>
   <production id="9649" count="1" enchant="0"/>      
   </item>
   <item id="40">
   <ingredient id="11974" count="10" enchant="0"/>
   <ingredient id="17167" count="1" enchant="0"/>
   <ingredient id="17168" count="1" enchant="0"/>
   <ingredient id="17169" count="1" enchant="0"/>
   <ingredient id="17170" count="1" enchant="0"/>
   <ingredient id="17171" count="1" enchant="0"/>   
   <production id="9656" count="1" enchant="0"/>
   <production id="9646" count="1" enchant="0"/>
   <production id="9647" count="1" enchant="0"/>
   <production id="9648" count="1" enchant="0"/>
   <production id="9649" count="1" enchant="0"/>    
   </item>
   <item id="41">
   <ingredient id="11974" count="10" enchant="0"/>
   <ingredient id="17172" count="1" enchant="0"/>
   <ingredient id="17173" count="1" enchant="0"/>
   <ingredient id="17174" count="1" enchant="0"/>
   <ingredient id="17175" count="1" enchant="0"/>  
   <production id="9656" count="1" enchant="0"/>
   <production id="9646" count="1" enchant="0"/>
   <production id="9647" count="1" enchant="0"/>
   <production id="9648" count="1" enchant="0"/>
   <production id="9649" count="1" enchant="0"/>      
   </item>
      <item id="42">
	  <ingredient id="11974" count="10" enchant="0"/>
   <ingredient id="17176" count="1" enchant="0"/>
   <ingredient id="17177" count="1" enchant="0"/>
   <ingredient id="17178" count="1" enchant="0"/>
   <ingredient id="17179" count="1" enchant="0"/>  
   <production id="9656" count="1" enchant="0"/>
   <production id="9646" count="1" enchant="0"/>
   <production id="9647" count="1" enchant="0"/>
   <production id="9648" count="1" enchant="0"/>
   <production id="9649" count="1" enchant="0"/>  
   </item> 
   <item id="43">
   <ingredient id="11974" count="10" enchant="0"/>
   <ingredient id="16500" count="1" enchant="0"/>
   <ingredient id="16502" count="1" enchant="0"/>
   <ingredient id="16504" count="1" enchant="0"/>
   <ingredient id="16506" count="1" enchant="0"/>
   <ingredient id="16508" count="1" enchant="0"/>   
   <production id="9656" count="1" enchant="0"/>
   <production id="9646" count="1" enchant="0"/>
   <production id="9647" count="1" enchant="0"/>
   <production id="9648" count="1" enchant="0"/>
   <production id="9649" count="1" enchant="0"/>    
   </item>
      <item id="44">
	  <ingredient id="11974" count="10" enchant="0"/>
   <ingredient id="26122" count="1" enchant="0"/>
   <ingredient id="28227" count="1" enchant="0"/>
   <ingredient id="28217" count="1" enchant="0"/>
   <ingredient id="28222" count="1" enchant="0"/>
 
   <production id="9656" count="1" enchant="0"/>
   <production id="9646" count="1" enchant="0"/>
   <production id="9647" count="1" enchant="0"/>
   <production id="9648" count="1" enchant="0"/>
   <production id="9649" count="1" enchant="0"/>   
   </item>
      <item id="45">
	  <ingredient id="11974" count="10" enchant="0"/>
   <ingredient id="28228" count="1" enchant="0"/>
   <ingredient id="26123" count="1" enchant="0"/>
   <ingredient id="28218" count="1" enchant="0"/>
   <ingredient id="28223" count="1" enchant="0"/>   
   <production id="9655" count="1" enchant="0"/>
   <production id="9650" count="1" enchant="0"/>
   <production id="9651" count="1" enchant="0"/>
   <production id="9652" count="1" enchant="0"/>
   <production id="9653" count="1" enchant="0"/>          
   </item> 
   <item id="46">
   <ingredient id="11974" count="10" enchant="0"/>
   <ingredient id="28229" count="1" enchant="0"/>
   <ingredient id="26124" count="1" enchant="0"/>
   <ingredient id="28219" count="1" enchant="0"/>
   <ingredient id="28224" count="1" enchant="0"/>   
   <production id="9655" count="1" enchant="0"/>
   <production id="9650" count="1" enchant="0"/>
   <production id="9651" count="1" enchant="0"/>
   <production id="9652" count="1" enchant="0"/>
   <production id="9653" count="1" enchant="0"/>     
   </item>
   <item id="47">
   <ingredient id="11974" count="10" enchant="0"/>
   <ingredient id="9666" count="1" enchant="0"/>
   <ingredient id="9657" count="1" enchant="0"/>
   <ingredient id="9658" count="1" enchant="0"/>
   <ingredient id="9659" count="1" enchant="0"/>
   <ingredient id="9660" count="1" enchant="0"/>   
   <production id="9655" count="1" enchant="0"/>
   <production id="9650" count="1" enchant="0"/>
   <production id="9651" count="1" enchant="0"/>
   <production id="9652" count="1" enchant="0"/>
   <production id="9653" count="1" enchant="0"/>     
   </item>
   <item id="48">
   <ingredient id="11974" count="10" enchant="0"/>
   <ingredient id="9665" count="1" enchant="0"/>
   <ingredient id="9661" count="1" enchant="0"/>
   <ingredient id="9662" count="1" enchant="0"/>
   <ingredient id="9663" count="1" enchant="0"/>
   <ingredient id="9664" count="1" enchant="0"/>   
   <production id="9655" count="1" enchant="0"/>
   <production id="9650" count="1" enchant="0"/>
   <production id="9651" count="1" enchant="0"/>
   <production id="9652" count="1" enchant="0"/>
   <production id="9653" count="1" enchant="0"/>    
   </item>
   <item id="49">
   <ingredient id="11974" count="10" enchant="0"/>
   <ingredient id="17180" count="1" enchant="0"/>
   <ingredient id="17134" count="1" enchant="0"/>
   <ingredient id="17135" count="1" enchant="0"/>
   <ingredient id="17136" count="1" enchant="0"/>
   <ingredient id="17137" count="1" enchant="0"/>   
   <production id="9655" count="1" enchant="0"/>
   <production id="9650" count="1" enchant="0"/>
   <production id="9651" count="1" enchant="0"/>
   <production id="9652" count="1" enchant="0"/>
   <production id="9653" count="1" enchant="0"/>  
   </item>
   <item id="50">
   <ingredient id="11974" count="10" enchant="0"/>
   <ingredient id="17182" count="1" enchant="0"/>
   <ingredient id="17144" count="1" enchant="0"/>
   <ingredient id="17145" count="1" enchant="0"/>
   <ingredient id="17146" count="1" enchant="0"/>
   <ingredient id="17147" count="1" enchant="0"/>   
   <production id="9655" count="1" enchant="0"/>
   <production id="9650" count="1" enchant="0"/>
   <production id="9651" count="1" enchant="0"/>
   <production id="9652" count="1" enchant="0"/>
   <production id="9653" count="1" enchant="0"/>       
   </item>
   <item id="51">
   <ingredient id="11974" count="10" enchant="0"/>
   <ingredient id="17167" count="1" enchant="0"/>
   <ingredient id="17168" count="1" enchant="0"/>
   <ingredient id="17169" count="1" enchant="0"/>
   <ingredient id="17170" count="1" enchant="0"/>
   <ingredient id="17171" count="1" enchant="0"/>   
   <production id="9655" count="1" enchant="0"/>
   <production id="9650" count="1" enchant="0"/>
   <production id="9651" count="1" enchant="0"/>
   <production id="9652" count="1" enchant="0"/>
   <production id="9653" count="1" enchant="0"/>     
   </item>
   <item id="52">
   <ingredient id="11974" count="10" enchant="0"/>
   <ingredient id="17172" count="1" enchant="0"/>
   <ingredient id="17173" count="1" enchant="0"/>
   <ingredient id="17174" count="1" enchant="0"/>
   <ingredient id="17175" count="1" enchant="0"/>  
   <production id="9655" count="1" enchant="0"/>
   <production id="9650" count="1" enchant="0"/>
   <production id="9651" count="1" enchant="0"/>
   <production id="9652" count="1" enchant="0"/>
   <production id="9653" count="1" enchant="0"/>       
   </item>
      <item id="53">
	  <ingredient id="11974" count="10" enchant="0"/>
   <ingredient id="17176" count="1" enchant="0"/>
   <ingredient id="17177" count="1" enchant="0"/>
   <ingredient id="17178" count="1" enchant="0"/>
   <ingredient id="17179" count="1" enchant="0"/>  
   <production id="9655" count="1" enchant="0"/>
   <production id="9650" count="1" enchant="0"/>
   <production id="9651" count="1" enchant="0"/>
   <production id="9652" count="1" enchant="0"/>
   <production id="9653" count="1" enchant="0"/>   
   </item> 
   <item id="54">
   <ingredient id="11974" count="10" enchant="0"/>
   <ingredient id="16500" count="1" enchant="0"/>
   <ingredient id="16502" count="1" enchant="0"/>
   <ingredient id="16504" count="1" enchant="0"/>
   <ingredient id="16506" count="1" enchant="0"/>
   <ingredient id="16508" count="1" enchant="0"/>   
   <production id="9655" count="1" enchant="0"/>
   <production id="9650" count="1" enchant="0"/>
   <production id="9651" count="1" enchant="0"/>
   <production id="9652" count="1" enchant="0"/>
   <production id="9653" count="1" enchant="0"/>     
   </item>
      <item id="55">
	  <ingredient id="11974" count="10" enchant="0"/>
   <ingredient id="26122" count="1" enchant="0"/>
   <ingredient id="28227" count="1" enchant="0"/>
   <ingredient id="28217" count="1" enchant="0"/>
   <ingredient id="28222" count="1" enchant="0"/>
 
   <production id="9655" count="1" enchant="0"/>
   <production id="9650" count="1" enchant="0"/>
   <production id="9651" count="1" enchant="0"/>
   <production id="9652" count="1" enchant="0"/>
   <production id="9653" count="1" enchant="0"/>    
   </item>
      <item id="56">
	  <ingredient id="11974" count="10" enchant="0"/>
   <ingredient id="28228" count="1" enchant="0"/>
   <ingredient id="26123" count="1" enchant="0"/>
   <ingredient id="28218" count="1" enchant="0"/>
   <ingredient id="28223" count="1" enchant="0"/>   
   <production id="17181" count="1" enchant="0"/>
   <production id="17139" count="1" enchant="0"/>
   <production id="17140" count="1" enchant="0"/>
   <production id="17141" count="1" enchant="0"/>
   <production id="17142" count="1" enchant="0"/>           
   </item> 
   <item id="57">
   <ingredient id="11974" count="10" enchant="0"/>
   <ingredient id="28229" count="1" enchant="0"/>
   <ingredient id="26124" count="1" enchant="0"/>
   <ingredient id="28219" count="1" enchant="0"/>
   <ingredient id="28224" count="1" enchant="0"/>   
   <production id="17181" count="1" enchant="0"/>
   <production id="17139" count="1" enchant="0"/>
   <production id="17140" count="1" enchant="0"/>
   <production id="17141" count="1" enchant="0"/>
   <production id="17142" count="1" enchant="0"/>      
   </item>
   <item id="58">
   <ingredient id="11974" count="10" enchant="0"/>
   <ingredient id="9666" count="1" enchant="0"/>
   <ingredient id="9657" count="1" enchant="0"/>
   <ingredient id="9658" count="1" enchant="0"/>
   <ingredient id="9659" count="1" enchant="0"/>
   <ingredient id="9660" count="1" enchant="0"/>   
   <production id="17181" count="1" enchant="0"/>
   <production id="17139" count="1" enchant="0"/>
   <production id="17140" count="1" enchant="0"/>
   <production id="17141" count="1" enchant="0"/>
   <production id="17142" count="1" enchant="0"/>      
   </item>
   <item id="59">
   <ingredient id="11974" count="10" enchant="0"/>
   <ingredient id="9665" count="1" enchant="0"/>
   <ingredient id="9661" count="1" enchant="0"/>
   <ingredient id="9662" count="1" enchant="0"/>
   <ingredient id="9663" count="1" enchant="0"/>
   <ingredient id="9664" count="1" enchant="0"/>   
   <production id="17181" count="1" enchant="0"/>
   <production id="17139" count="1" enchant="0"/>
   <production id="17140" count="1" enchant="0"/>
   <production id="17141" count="1" enchant="0"/>
   <production id="17142" count="1" enchant="0"/>     
   </item>
   <item id="60">
   <ingredient id="11974" count="10" enchant="0"/>
   <ingredient id="17180" count="1" enchant="0"/>
   <ingredient id="17134" count="1" enchant="0"/>
   <ingredient id="17135" count="1" enchant="0"/>
   <ingredient id="17136" count="1" enchant="0"/>
   <ingredient id="17137" count="1" enchant="0"/>   
   <production id="17181" count="1" enchant="0"/>
   <production id="17139" count="1" enchant="0"/>
   <production id="17140" count="1" enchant="0"/>
   <production id="17141" count="1" enchant="0"/>
   <production id="17142" count="1" enchant="0"/>   
   </item>
   <item id="61">
   <ingredient id="11974" count="10" enchant="0"/>
   <ingredient id="17182" count="1" enchant="0"/>
   <ingredient id="17144" count="1" enchant="0"/>
   <ingredient id="17145" count="1" enchant="0"/>
   <ingredient id="17146" count="1" enchant="0"/>
   <ingredient id="17147" count="1" enchant="0"/>   
   <production id="17181" count="1" enchant="0"/>
   <production id="17139" count="1" enchant="0"/>
   <production id="17140" count="1" enchant="0"/>
   <production id="17141" count="1" enchant="0"/>
   <production id="17142" count="1" enchant="0"/>        
   </item>
   <item id="62">
   <ingredient id="11974" count="10" enchant="0"/>
   <ingredient id="17167" count="1" enchant="0"/>
   <ingredient id="17168" count="1" enchant="0"/>
   <ingredient id="17169" count="1" enchant="0"/>
   <ingredient id="17170" count="1" enchant="0"/>
   <ingredient id="17171" count="1" enchant="0"/>   
   <production id="17181" count="1" enchant="0"/>
   <production id="17139" count="1" enchant="0"/>
   <production id="17140" count="1" enchant="0"/>
   <production id="17141" count="1" enchant="0"/>
   <production id="17142" count="1" enchant="0"/>     
   </item>
   <item id="63">
   <ingredient id="11974" count="10" enchant="0"/>
   <ingredient id="17172" count="1" enchant="0"/>
   <ingredient id="17173" count="1" enchant="0"/>
   <ingredient id="17174" count="1" enchant="0"/>
   <ingredient id="17175" count="1" enchant="0"/>  
   <production id="17181" count="1" enchant="0"/>
   <production id="17139" count="1" enchant="0"/>
   <production id="17140" count="1" enchant="0"/>
   <production id="17141" count="1" enchant="0"/>
   <production id="17142" count="1" enchant="0"/>        
   </item>
      <item id="64">
	  <ingredient id="11974" count="10" enchant="0"/>
   <ingredient id="17176" count="1" enchant="0"/>
   <ingredient id="17177" count="1" enchant="0"/>
   <ingredient id="17178" count="1" enchant="0"/>
   <ingredient id="17179" count="1" enchant="0"/>  
   <production id="17181" count="1" enchant="0"/>
   <production id="17139" count="1" enchant="0"/>
   <production id="17140" count="1" enchant="0"/>
   <production id="17141" count="1" enchant="0"/>
   <production id="17142" count="1" enchant="0"/>    
   </item> 
   <item id="65">
   <ingredient id="11974" count="10" enchant="0"/>
   <ingredient id="16500" count="1" enchant="0"/>
   <ingredient id="16502" count="1" enchant="0"/>
   <ingredient id="16504" count="1" enchant="0"/>
   <ingredient id="16506" count="1" enchant="0"/>
   <ingredient id="16508" count="1" enchant="0"/>   
   <production id="17181" count="1" enchant="0"/>
   <production id="17139" count="1" enchant="0"/>
   <production id="17140" count="1" enchant="0"/>
   <production id="17141" count="1" enchant="0"/>
   <production id="17142" count="1" enchant="0"/>      
   </item>
      <item id="66">
	  <ingredient id="11974" count="10" enchant="0"/>
   <ingredient id="26122" count="1" enchant="0"/>
   <ingredient id="28227" count="1" enchant="0"/>
   <ingredient id="28217" count="1" enchant="0"/>
   <ingredient id="28222" count="1" enchant="0"/>
 
   <production id="17181" count="1" enchant="0"/>
   <production id="17139" count="1" enchant="0"/>
   <production id="17140" count="1" enchant="0"/>
   <production id="17141" count="1" enchant="0"/>
   <production id="17142" count="1" enchant="0"/>     
   </item>
      <item id="67">
	  <ingredient id="11974" count="10" enchant="0"/>
   <ingredient id="28228" count="1" enchant="0"/>
   <ingredient id="26123" count="1" enchant="0"/>
   <ingredient id="28218" count="1" enchant="0"/>
   <ingredient id="28223" count="1" enchant="0"/>   
   <production id="17183" count="1" enchant="0"/>
   <production id="17149" count="1" enchant="0"/>
   <production id="17150" count="1" enchant="0"/>
   <production id="17151" count="1" enchant="0"/>
   <production id="17152" count="1" enchant="0"/>           
   </item> 
   <item id="68">
   <ingredient id="11974" count="10" enchant="0"/>
   <ingredient id="28229" count="1" enchant="0"/>
   <ingredient id="26124" count="1" enchant="0"/>
   <ingredient id="28219" count="1" enchant="0"/>
   <ingredient id="28224" count="1" enchant="0"/>   
   <production id="17183" count="1" enchant="0"/>
   <production id="17149" count="1" enchant="0"/>
   <production id="17150" count="1" enchant="0"/>
   <production id="17151" count="1" enchant="0"/>
   <production id="17152" count="1" enchant="0"/>      
   </item>
   <item id="69">
   <ingredient id="11974" count="10" enchant="0"/>
   <ingredient id="9666" count="1" enchant="0"/>
   <ingredient id="9657" count="1" enchant="0"/>
   <ingredient id="9658" count="1" enchant="0"/>
   <ingredient id="9659" count="1" enchant="0"/>
   <ingredient id="9660" count="1" enchant="0"/>   
   <production id="17183" count="1" enchant="0"/>
   <production id="17149" count="1" enchant="0"/>
   <production id="17150" count="1" enchant="0"/>
   <production id="17151" count="1" enchant="0"/>
   <production id="17152" count="1" enchant="0"/>      
   </item>
   <item id="70">
   <ingredient id="11974" count="10" enchant="0"/>
   <ingredient id="9665" count="1" enchant="0"/>
   <ingredient id="9661" count="1" enchant="0"/>
   <ingredient id="9662" count="1" enchant="0"/>
   <ingredient id="9663" count="1" enchant="0"/>
   <ingredient id="9664" count="1" enchant="0"/>   
   <production id="17183" count="1" enchant="0"/>
   <production id="17149" count="1" enchant="0"/>
   <production id="17150" count="1" enchant="0"/>
   <production id="17151" count="1" enchant="0"/>
   <production id="17152" count="1" enchant="0"/>     
   </item>
   <item id="71">
   <ingredient id="11974" count="10" enchant="0"/>
   <ingredient id="17180" count="1" enchant="0"/>
   <ingredient id="17134" count="1" enchant="0"/>
   <ingredient id="17135" count="1" enchant="0"/>
   <ingredient id="17136" count="1" enchant="0"/>
   <ingredient id="17137" count="1" enchant="0"/>   
   <production id="17183" count="1" enchant="0"/>
   <production id="17149" count="1" enchant="0"/>
   <production id="17150" count="1" enchant="0"/>
   <production id="17151" count="1" enchant="0"/>
   <production id="17152" count="1" enchant="0"/>   
   </item>
   <item id="72">
   <ingredient id="11974" count="10" enchant="0"/>
   <ingredient id="17182" count="1" enchant="0"/>
   <ingredient id="17144" count="1" enchant="0"/>
   <ingredient id="17145" count="1" enchant="0"/>
   <ingredient id="17146" count="1" enchant="0"/>
   <ingredient id="17147" count="1" enchant="0"/>   
   <production id="17183" count="1" enchant="0"/>
   <production id="17149" count="1" enchant="0"/>
   <production id="17150" count="1" enchant="0"/>
   <production id="17151" count="1" enchant="0"/>
   <production id="17152" count="1" enchant="0"/>        
   </item>
   <item id="73">
   <ingredient id="11974" count="10" enchant="0"/>
   <ingredient id="17167" count="1" enchant="0"/>
   <ingredient id="17168" count="1" enchant="0"/>
   <ingredient id="17169" count="1" enchant="0"/>
   <ingredient id="17170" count="1" enchant="0"/>
   <ingredient id="17171" count="1" enchant="0"/>   
   <production id="17183" count="1" enchant="0"/>
   <production id="17149" count="1" enchant="0"/>
   <production id="17150" count="1" enchant="0"/>
   <production id="17151" count="1" enchant="0"/>
   <production id="17152" count="1" enchant="0"/>     
   </item>
   <item id="74">
   <ingredient id="11974" count="10" enchant="0"/>
   <ingredient id="17172" count="1" enchant="0"/>
   <ingredient id="17173" count="1" enchant="0"/>
   <ingredient id="17174" count="1" enchant="0"/>
   <ingredient id="17175" count="1" enchant="0"/>  
   <production id="17183" count="1" enchant="0"/>
   <production id="17149" count="1" enchant="0"/>
   <production id="17150" count="1" enchant="0"/>
   <production id="17151" count="1" enchant="0"/>
   <production id="17152" count="1" enchant="0"/>        
   </item>
      <item id="75">
	  <ingredient id="11974" count="10" enchant="0"/>
   <ingredient id="17176" count="1" enchant="0"/>
   <ingredient id="17177" count="1" enchant="0"/>
   <ingredient id="17178" count="1" enchant="0"/>
   <ingredient id="17179" count="1" enchant="0"/>  
   <production id="17183" count="1" enchant="0"/>
   <production id="17149" count="1" enchant="0"/>
   <production id="17150" count="1" enchant="0"/>
   <production id="17151" count="1" enchant="0"/>
   <production id="17152" count="1" enchant="0"/>    
   </item> 
   <item id="76">
   <ingredient id="11974" count="10" enchant="0"/>
   <ingredient id="16500" count="1" enchant="0"/>
   <ingredient id="16502" count="1" enchant="0"/>
   <ingredient id="16504" count="1" enchant="0"/>
   <ingredient id="16506" count="1" enchant="0"/>
   <ingredient id="16508" count="1" enchant="0"/>   
   <production id="17183" count="1" enchant="0"/>
   <production id="17149" count="1" enchant="0"/>
   <production id="17150" count="1" enchant="0"/>
   <production id="17151" count="1" enchant="0"/>
   <production id="17152" count="1" enchant="0"/>      
   </item>
      <item id="77">
	  <ingredient id="11974" count="10" enchant="0"/>
   <ingredient id="26122" count="1" enchant="0"/>
   <ingredient id="28227" count="1" enchant="0"/>
   <ingredient id="28217" count="1" enchant="0"/>
   <ingredient id="28222" count="1" enchant="0"/>
 
   <production id="17183" count="1" enchant="0"/>
   <production id="17149" count="1" enchant="0"/>
   <production id="17150" count="1" enchant="0"/>
   <production id="17151" count="1" enchant="0"/>
   <production id="17152" count="1" enchant="0"/>    
   </item>
      <item id="78">
	  <ingredient id="11974" count="10" enchant="0"/>
   <ingredient id="28228" count="1" enchant="0"/>
   <ingredient id="26123" count="1" enchant="0"/>
   <ingredient id="28218" count="1" enchant="0"/>
   <ingredient id="28223" count="1" enchant="0"/>   
   <production id="17162" count="1" enchant="0"/>
   <production id="17163" count="1" enchant="0"/>
   <production id="17164" count="1" enchant="0"/>
   <production id="17165" count="1" enchant="0"/>
   <production id="17166" count="1" enchant="0"/>           
   </item> 
   <item id="79">
   <ingredient id="11974" count="10" enchant="0"/>
   <ingredient id="28229" count="1" enchant="0"/>
   <ingredient id="26124" count="1" enchant="0"/>
   <ingredient id="28219" count="1" enchant="0"/>
   <ingredient id="28224" count="1" enchant="0"/>   
   <production id="17162" count="1" enchant="0"/>
   <production id="17163" count="1" enchant="0"/>
   <production id="17164" count="1" enchant="0"/>
   <production id="17165" count="1" enchant="0"/>
   <production id="17166" count="1" enchant="0"/>      
   </item>
   <item id="80">
   <ingredient id="11974" count="10" enchant="0"/>
   <ingredient id="9666" count="1" enchant="0"/>
   <ingredient id="9657" count="1" enchant="0"/>
   <ingredient id="9658" count="1" enchant="0"/>
   <ingredient id="9659" count="1" enchant="0"/>
   <ingredient id="9660" count="1" enchant="0"/>   
   <production id="17162" count="1" enchant="0"/>
   <production id="17163" count="1" enchant="0"/>
   <production id="17164" count="1" enchant="0"/>
   <production id="17165" count="1" enchant="0"/>
   <production id="17166" count="1" enchant="0"/>      
   </item>
   <item id="81">
   <ingredient id="11974" count="10" enchant="0"/>
   <ingredient id="9665" count="1" enchant="0"/>
   <ingredient id="9661" count="1" enchant="0"/>
   <ingredient id="9662" count="1" enchant="0"/>
   <ingredient id="9663" count="1" enchant="0"/>
   <ingredient id="9664" count="1" enchant="0"/>   
   <production id="17162" count="1" enchant="0"/>
   <production id="17163" count="1" enchant="0"/>
   <production id="17164" count="1" enchant="0"/>
   <production id="17165" count="1" enchant="0"/>
   <production id="17166" count="1" enchant="0"/>     
   </item>
   <item id="82">
   <ingredient id="11974" count="10" enchant="0"/>
   <ingredient id="17180" count="1" enchant="0"/>
   <ingredient id="17134" count="1" enchant="0"/>
   <ingredient id="17135" count="1" enchant="0"/>
   <ingredient id="17136" count="1" enchant="0"/>
   <ingredient id="17137" count="1" enchant="0"/>   
   <production id="17162" count="1" enchant="0"/>
   <production id="17163" count="1" enchant="0"/>
   <production id="17164" count="1" enchant="0"/>
   <production id="17165" count="1" enchant="0"/>
   <production id="17166" count="1" enchant="0"/>  
   </item>
   <item id="83">
   <ingredient id="11974" count="10" enchant="0"/>
   <ingredient id="17182" count="1" enchant="0"/>
   <ingredient id="17144" count="1" enchant="0"/>
   <ingredient id="17145" count="1" enchant="0"/>
   <ingredient id="17146" count="1" enchant="0"/>
   <ingredient id="17147" count="1" enchant="0"/>   
   <production id="17162" count="1" enchant="0"/>
   <production id="17163" count="1" enchant="0"/>
   <production id="17164" count="1" enchant="0"/>
   <production id="17165" count="1" enchant="0"/>
   <production id="17166" count="1" enchant="0"/>        
   </item>
   <item id="84">
   <ingredient id="11974" count="10" enchant="0"/>
   <ingredient id="17167" count="1" enchant="0"/>
   <ingredient id="17168" count="1" enchant="0"/>
   <ingredient id="17169" count="1" enchant="0"/>
   <ingredient id="17170" count="1" enchant="0"/>
   <ingredient id="17171" count="1" enchant="0"/>   
   <production id="17162" count="1" enchant="0"/>
   <production id="17163" count="1" enchant="0"/>
   <production id="17164" count="1" enchant="0"/>
   <production id="17165" count="1" enchant="0"/>
   <production id="17166" count="1" enchant="0"/>     
   </item>
   <item id="85">
   <ingredient id="11974" count="10" enchant="0"/>
   <ingredient id="17172" count="1" enchant="0"/>
   <ingredient id="17173" count="1" enchant="0"/>
   <ingredient id="17174" count="1" enchant="0"/>
   <ingredient id="17175" count="1" enchant="0"/>  
   <production id="17162" count="1" enchant="0"/>
   <production id="17163" count="1" enchant="0"/>
   <production id="17164" count="1" enchant="0"/>
   <production id="17165" count="1" enchant="0"/>
   <production id="17166" count="1" enchant="0"/>        
   </item>
      <item id="86">
	  <ingredient id="11974" count="10" enchant="0"/>
   <ingredient id="17176" count="1" enchant="0"/>
   <ingredient id="17177" count="1" enchant="0"/>
   <ingredient id="17178" count="1" enchant="0"/>
   <ingredient id="17179" count="1" enchant="0"/>  
   <production id="17162" count="1" enchant="0"/>
   <production id="17163" count="1" enchant="0"/>
   <production id="17164" count="1" enchant="0"/>
   <production id="17165" count="1" enchant="0"/>
   <production id="17166" count="1" enchant="0"/>    
   </item> 
   <item id="87">
   <ingredient id="11974" count="10" enchant="0"/>
   <ingredient id="16500" count="1" enchant="0"/>
   <ingredient id="16502" count="1" enchant="0"/>
   <ingredient id="16504" count="1" enchant="0"/>
   <ingredient id="16506" count="1" enchant="0"/>
   <ingredient id="16508" count="1" enchant="0"/>   
   <production id="17162" count="1" enchant="0"/>
   <production id="17163" count="1" enchant="0"/>
   <production id="17164" count="1" enchant="0"/>
   <production id="17165" count="1" enchant="0"/>
   <production id="17166" count="1" enchant="0"/>      
   </item>
      <item id="88">
	  <ingredient id="11974" count="10" enchant="0"/>
   <ingredient id="26122" count="1" enchant="0"/>
   <ingredient id="28227" count="1" enchant="0"/>
   <ingredient id="28217" count="1" enchant="0"/>
   <ingredient id="28222" count="1" enchant="0"/>
 
   <production id="17162" count="1" enchant="0"/>
   <production id="17163" count="1" enchant="0"/>
   <production id="17164" count="1" enchant="0"/>
   <production id="17165" count="1" enchant="0"/>
   <production id="17166" count="1" enchant="0"/>    
   </item>
      <item id="89">
	  <ingredient id="11974" count="10" enchant="0"/>
   <ingredient id="28228" count="1" enchant="0"/>
   <ingredient id="26123" count="1" enchant="0"/>
   <ingredient id="28218" count="1" enchant="0"/>
   <ingredient id="28223" count="1" enchant="0"/>   
   <production id="17154" count="1" enchant="0"/>
   <production id="17155" count="1" enchant="0"/>
   <production id="17156" count="1" enchant="0"/>
   <production id="17157" count="1" enchant="0"/>            
   </item> 
   <item id="90">
   <ingredient id="11974" count="10" enchant="0"/>
   <ingredient id="28229" count="1" enchant="0"/>
   <ingredient id="26124" count="1" enchant="0"/>
   <ingredient id="28219" count="1" enchant="0"/>
   <ingredient id="28224" count="1" enchant="0"/>   
   <production id="17154" count="1" enchant="0"/>
   <production id="17155" count="1" enchant="0"/>
   <production id="17156" count="1" enchant="0"/>
   <production id="17157" count="1" enchant="0"/>        
   </item>
   <item id="91">
   <ingredient id="11974" count="10" enchant="0"/>
   <ingredient id="9666" count="1" enchant="0"/>
   <ingredient id="9657" count="1" enchant="0"/>
   <ingredient id="9658" count="1" enchant="0"/>
   <ingredient id="9659" count="1" enchant="0"/>
   <ingredient id="9660" count="1" enchant="0"/>   
   <production id="17154" count="1" enchant="0"/>
   <production id="17155" count="1" enchant="0"/>
   <production id="17156" count="1" enchant="0"/>
   <production id="17157" count="1" enchant="0"/>        
   </item>
   <item id="92">
   <ingredient id="11974" count="10" enchant="0"/>
   <ingredient id="9665" count="1" enchant="0"/>
   <ingredient id="9661" count="1" enchant="0"/>
   <ingredient id="9662" count="1" enchant="0"/>
   <ingredient id="9663" count="1" enchant="0"/>
   <ingredient id="9664" count="1" enchant="0"/>   
   <production id="17154" count="1" enchant="0"/>
   <production id="17155" count="1" enchant="0"/>
   <production id="17156" count="1" enchant="0"/>
   <production id="17157" count="1" enchant="0"/>       
   </item>
   <item id="93">
   <ingredient id="11974" count="10" enchant="0"/>
   <ingredient id="17180" count="1" enchant="0"/>
   <ingredient id="17134" count="1" enchant="0"/>
   <ingredient id="17135" count="1" enchant="0"/>
   <ingredient id="17136" count="1" enchant="0"/>
   <ingredient id="17137" count="1" enchant="0"/>   
   <production id="17154" count="1" enchant="0"/>
   <production id="17155" count="1" enchant="0"/>
   <production id="17156" count="1" enchant="0"/>
   <production id="17157" count="1" enchant="0"/>    
   </item>
   <item id="94">
   <ingredient id="11974" count="10" enchant="0"/>
   <ingredient id="17182" count="1" enchant="0"/>
   <ingredient id="17144" count="1" enchant="0"/>
   <ingredient id="17145" count="1" enchant="0"/>
   <ingredient id="17146" count="1" enchant="0"/>
   <ingredient id="17147" count="1" enchant="0"/>   
   <production id="17154" count="1" enchant="0"/>
   <production id="17155" count="1" enchant="0"/>
   <production id="17156" count="1" enchant="0"/>
   <production id="17157" count="1" enchant="0"/>         
   </item>
   <item id="95">
   <ingredient id="11974" count="10" enchant="0"/>
   <ingredient id="17167" count="1" enchant="0"/>
   <ingredient id="17168" count="1" enchant="0"/>
   <ingredient id="17169" count="1" enchant="0"/>
   <ingredient id="17170" count="1" enchant="0"/>
   <ingredient id="17171" count="1" enchant="0"/>   
   <production id="17154" count="1" enchant="0"/>
   <production id="17155" count="1" enchant="0"/>
   <production id="17156" count="1" enchant="0"/>
   <production id="17157" count="1" enchant="0"/>      
   </item>
   <item id="96">
   <ingredient id="11974" count="10" enchant="0"/>
   <ingredient id="17172" count="1" enchant="0"/>
   <ingredient id="17173" count="1" enchant="0"/>
   <ingredient id="17174" count="1" enchant="0"/>
   <ingredient id="17175" count="1" enchant="0"/>  
   <production id="17154" count="1" enchant="0"/>
   <production id="17155" count="1" enchant="0"/>
   <production id="17156" count="1" enchant="0"/>
   <production id="17157" count="1" enchant="0"/>         
   </item>
      <item id="97">
	  <ingredient id="11974" count="10" enchant="0"/>
   <ingredient id="17176" count="1" enchant="0"/>
   <ingredient id="17177" count="1" enchant="0"/>
   <ingredient id="17178" count="1" enchant="0"/>
   <ingredient id="17179" count="1" enchant="0"/>  
   <production id="17154" count="1" enchant="0"/>
   <production id="17155" count="1" enchant="0"/>
   <production id="17156" count="1" enchant="0"/>
   <production id="17157" count="1" enchant="0"/>      
   </item> 
   <item id="98">
   <ingredient id="11974" count="10" enchant="0"/>
   <ingredient id="16500" count="1" enchant="0"/>
   <ingredient id="16502" count="1" enchant="0"/>
   <ingredient id="16504" count="1" enchant="0"/>
   <ingredient id="16506" count="1" enchant="0"/>
   <ingredient id="16508" count="1" enchant="0"/>   
   <production id="17154" count="1" enchant="0"/>
   <production id="17155" count="1" enchant="0"/>
   <production id="17156" count="1" enchant="0"/>
   <production id="17157" count="1" enchant="0"/>        
   </item>
      <item id="99">
	  <ingredient id="11974" count="10" enchant="0"/>
   <ingredient id="26122" count="1" enchant="0"/>
   <ingredient id="28227" count="1" enchant="0"/>
   <ingredient id="28217" count="1" enchant="0"/>
   <ingredient id="28222" count="1" enchant="0"/>
 
   <production id="17154" count="1" enchant="0"/>
   <production id="17155" count="1" enchant="0"/>
   <production id="17156" count="1" enchant="0"/>
   <production id="17157" count="1" enchant="0"/>     
   </item>
   
      <item id="100">
	  <ingredient id="11974" count="10" enchant="0"/>
   <ingredient id="28228" count="1" enchant="0"/>
   <ingredient id="26123" count="1" enchant="0"/>
   <ingredient id="28218" count="1" enchant="0"/>
   <ingredient id="28223" count="1" enchant="0"/>   
   <production id="17158" count="1" enchant="0"/>
   <production id="17159" count="1" enchant="0"/>
   <production id="17160" count="1" enchant="0"/>
   <production id="17161" count="1" enchant="0"/>            
   </item> 
   <item id="101">
   <ingredient id="11974" count="10" enchant="0"/>
   <ingredient id="28229" count="1" enchant="0"/>
   <ingredient id="26124" count="1" enchant="0"/>
   <ingredient id="28219" count="1" enchant="0"/>
   <ingredient id="28224" count="1" enchant="0"/>   
   <production id="17158" count="1" enchant="0"/>
   <production id="17159" count="1" enchant="0"/>
   <production id="17160" count="1" enchant="0"/>
   <production id="17161" count="1" enchant="0"/>        
   </item>
   <item id="102">
   <ingredient id="11974" count="10" enchant="0"/>
   <ingredient id="9666" count="1" enchant="0"/>
   <ingredient id="9657" count="1" enchant="0"/>
   <ingredient id="9658" count="1" enchant="0"/>
   <ingredient id="9659" count="1" enchant="0"/>
   <ingredient id="9660" count="1" enchant="0"/>   
   <production id="17158" count="1" enchant="0"/>
   <production id="17159" count="1" enchant="0"/>
   <production id="17160" count="1" enchant="0"/>
   <production id="17161" count="1" enchant="0"/>        
   </item>
   <item id="103">
   <ingredient id="11974" count="10" enchant="0"/>
   <ingredient id="9665" count="1" enchant="0"/>
   <ingredient id="9661" count="1" enchant="0"/>
   <ingredient id="9662" count="1" enchant="0"/>
   <ingredient id="9663" count="1" enchant="0"/>
   <ingredient id="9664" count="1" enchant="0"/>   
   <production id="17158" count="1" enchant="0"/>
   <production id="17159" count="1" enchant="0"/>
   <production id="17160" count="1" enchant="0"/>
   <production id="17161" count="1" enchant="0"/>       
   </item>
   <item id="104">
   <ingredient id="11974" count="10" enchant="0"/>
   <ingredient id="17180" count="1" enchant="0"/>
   <ingredient id="17134" count="1" enchant="0"/>
   <ingredient id="17135" count="1" enchant="0"/>
   <ingredient id="17136" count="1" enchant="0"/>
   <ingredient id="17137" count="1" enchant="0"/>   
   <production id="17158" count="1" enchant="0"/>
   <production id="17159" count="1" enchant="0"/>
   <production id="17160" count="1" enchant="0"/>
   <production id="17161" count="1" enchant="0"/>     
   </item>
   <item id="105">
   <ingredient id="11974" count="10" enchant="0"/>
   <ingredient id="17182" count="1" enchant="0"/>
   <ingredient id="17144" count="1" enchant="0"/>
   <ingredient id="17145" count="1" enchant="0"/>
   <ingredient id="17146" count="1" enchant="0"/>
   <ingredient id="17147" count="1" enchant="0"/>   
   <production id="17158" count="1" enchant="0"/>
   <production id="17159" count="1" enchant="0"/>
   <production id="17160" count="1" enchant="0"/>
   <production id="17161" count="1" enchant="0"/>          
   </item>
   <item id="106">
   <ingredient id="11974" count="10" enchant="0"/>
   <ingredient id="17167" count="1" enchant="0"/>
   <ingredient id="17168" count="1" enchant="0"/>
   <ingredient id="17169" count="1" enchant="0"/>
   <ingredient id="17170" count="1" enchant="0"/>
   <ingredient id="17171" count="1" enchant="0"/>   
   <production id="17158" count="1" enchant="0"/>
   <production id="17159" count="1" enchant="0"/>
   <production id="17160" count="1" enchant="0"/>
   <production id="17161" count="1" enchant="0"/>      
   </item>
   <item id="107">
   <ingredient id="11974" count="10" enchant="0"/>
   <ingredient id="17172" count="1" enchant="0"/>
   <ingredient id="17173" count="1" enchant="0"/>
   <ingredient id="17174" count="1" enchant="0"/>
   <ingredient id="17175" count="1" enchant="0"/>  
   <production id="17158" count="1" enchant="0"/>
   <production id="17159" count="1" enchant="0"/>
   <production id="17160" count="1" enchant="0"/>
   <production id="17161" count="1" enchant="0"/>         
   </item>
      <item id="108">
	  <ingredient id="11974" count="10" enchant="0"/>
   <ingredient id="17176" count="1" enchant="0"/>
   <ingredient id="17177" count="1" enchant="0"/>
   <ingredient id="17178" count="1" enchant="0"/>
   <ingredient id="17179" count="1" enchant="0"/>  
   <production id="17158" count="1" enchant="0"/>
   <production id="17159" count="1" enchant="0"/>
   <production id="17160" count="1" enchant="0"/>
   <production id="17161" count="1" enchant="0"/>      
   </item> 
   <item id="109">
   <ingredient id="11974" count="10" enchant="0"/>
   <ingredient id="16500" count="1" enchant="0"/>
   <ingredient id="16502" count="1" enchant="0"/>
   <ingredient id="16504" count="1" enchant="0"/>
   <ingredient id="16506" count="1" enchant="0"/>
   <ingredient id="16508" count="1" enchant="0"/>   
   <production id="17158" count="1" enchant="0"/>
   <production id="17159" count="1" enchant="0"/>
   <production id="17160" count="1" enchant="0"/>
   <production id="17161" count="1" enchant="0"/>        
   </item>
      <item id="110">
	  <ingredient id="11974" count="10" enchant="0"/>
   <ingredient id="26122" count="1" enchant="0"/>
   <ingredient id="28227" count="1" enchant="0"/>
   <ingredient id="28217" count="1" enchant="0"/>
   <ingredient id="28222" count="1" enchant="0"/>
 
   <production id="17158" count="1" enchant="0"/>
   <production id="17159" count="1" enchant="0"/>
   <production id="17160" count="1" enchant="0"/>
   <production id="17161" count="1" enchant="0"/>     
   </item>
   
      <item id="111">
	  <ingredient id="11974" count="10" enchant="0"/>
   <ingredient id="28228" count="1" enchant="0"/>
   <ingredient id="26123" count="1" enchant="0"/>
   <ingredient id="28218" count="1" enchant="0"/>
   <ingredient id="28223" count="1" enchant="0"/>   
   <production id="16501" count="1" enchant="0"/>
   <production id="16503" count="1" enchant="0"/>
   <production id="16505" count="1" enchant="0"/>
   <production id="16507" count="1" enchant="0"/>
   <production id="16509" count="1" enchant="0"/>           
   </item> 
   <item id="112">
   <ingredient id="11974" count="10" enchant="0"/>
   <ingredient id="28229" count="1" enchant="0"/>
   <ingredient id="26124" count="1" enchant="0"/>
   <ingredient id="28219" count="1" enchant="0"/>
   <ingredient id="28224" count="1" enchant="0"/>   
   <production id="16501" count="1" enchant="0"/>
   <production id="16503" count="1" enchant="0"/>
   <production id="16505" count="1" enchant="0"/>
   <production id="16507" count="1" enchant="0"/>
   <production id="16509" count="1" enchant="0"/>       
   </item>
   <item id="113">
   <ingredient id="11974" count="10" enchant="0"/>
   <ingredient id="9666" count="1" enchant="0"/>
   <ingredient id="9657" count="1" enchant="0"/>
   <ingredient id="9658" count="1" enchant="0"/>
   <ingredient id="9659" count="1" enchant="0"/>
   <ingredient id="9660" count="1" enchant="0"/>   
   <production id="16501" count="1" enchant="0"/>
   <production id="16503" count="1" enchant="0"/>
   <production id="16505" count="1" enchant="0"/>
   <production id="16507" count="1" enchant="0"/>
   <production id="16509" count="1" enchant="0"/>        
   </item>
   <item id="114">
   <ingredient id="11974" count="10" enchant="0"/>
   <ingredient id="9665" count="1" enchant="0"/>
   <ingredient id="9661" count="1" enchant="0"/>
   <ingredient id="9662" count="1" enchant="0"/>
   <ingredient id="9663" count="1" enchant="0"/>
   <ingredient id="9664" count="1" enchant="0"/>   
   <production id="16501" count="1" enchant="0"/>
   <production id="16503" count="1" enchant="0"/>
   <production id="16505" count="1" enchant="0"/>
   <production id="16507" count="1" enchant="0"/>
   <production id="16509" count="1" enchant="0"/>       
   </item>
   <item id="115">
   <ingredient id="11974" count="10" enchant="0"/>
   <ingredient id="17180" count="1" enchant="0"/>
   <ingredient id="17134" count="1" enchant="0"/>
   <ingredient id="17135" count="1" enchant="0"/>
   <ingredient id="17136" count="1" enchant="0"/>
   <ingredient id="17137" count="1" enchant="0"/>   
   <production id="16501" count="1" enchant="0"/>
   <production id="16503" count="1" enchant="0"/>
   <production id="16505" count="1" enchant="0"/>
   <production id="16507" count="1" enchant="0"/>
   <production id="16509" count="1" enchant="0"/>    
   </item>
   <item id="116">
   <ingredient id="11974" count="10" enchant="0"/>
   <ingredient id="17182" count="1" enchant="0"/>
   <ingredient id="17144" count="1" enchant="0"/>
   <ingredient id="17145" count="1" enchant="0"/>
   <ingredient id="17146" count="1" enchant="0"/>
   <ingredient id="17147" count="1" enchant="0"/>   
   <production id="16501" count="1" enchant="0"/>
   <production id="16503" count="1" enchant="0"/>
   <production id="16505" count="1" enchant="0"/>
   <production id="16507" count="1" enchant="0"/>
   <production id="16509" count="1" enchant="0"/>         
   </item>
   <item id="117">
   <ingredient id="11974" count="10" enchant="0"/>
   <ingredient id="17167" count="1" enchant="0"/>
   <ingredient id="17168" count="1" enchant="0"/>
   <ingredient id="17169" count="1" enchant="0"/>
   <ingredient id="17170" count="1" enchant="0"/>
   <ingredient id="17171" count="1" enchant="0"/>   
   <production id="16501" count="1" enchant="0"/>
   <production id="16503" count="1" enchant="0"/>
   <production id="16505" count="1" enchant="0"/>
   <production id="16507" count="1" enchant="0"/>
   <production id="16509" count="1" enchant="0"/>      
   </item>
   <item id="118">
   <ingredient id="11974" count="10" enchant="0"/>
   <ingredient id="17172" count="1" enchant="0"/>
   <ingredient id="17173" count="1" enchant="0"/>
   <ingredient id="17174" count="1" enchant="0"/>
   <ingredient id="17175" count="1" enchant="0"/>  
   <production id="16501" count="1" enchant="0"/>
   <production id="16503" count="1" enchant="0"/>
   <production id="16505" count="1" enchant="0"/>
   <production id="16507" count="1" enchant="0"/>
   <production id="16509" count="1" enchant="0"/>         
   </item>
      <item id="119">
	  <ingredient id="11974" count="10" enchant="0"/>
   <ingredient id="17176" count="1" enchant="0"/>
   <ingredient id="17177" count="1" enchant="0"/>
   <ingredient id="17178" count="1" enchant="0"/>
   <ingredient id="17179" count="1" enchant="0"/>  
   <production id="16501" count="1" enchant="0"/>
   <production id="16503" count="1" enchant="0"/>
   <production id="16505" count="1" enchant="0"/>
   <production id="16507" count="1" enchant="0"/>
   <production id="16509" count="1" enchant="0"/>      
   </item> 
   <item id="120">
   <ingredient id="11974" count="10" enchant="0"/>
   <ingredient id="16500" count="1" enchant="0"/>
   <ingredient id="16502" count="1" enchant="0"/>
   <ingredient id="16504" count="1" enchant="0"/>
   <ingredient id="16506" count="1" enchant="0"/>
   <ingredient id="16508" count="1" enchant="0"/>   
   <production id="16501" count="1" enchant="0"/>
   <production id="16503" count="1" enchant="0"/>
   <production id="16505" count="1" enchant="0"/>
   <production id="16507" count="1" enchant="0"/>
   <production id="16509" count="1" enchant="0"/>       
   </item>
      <item id="121">
	  <ingredient id="11974" count="10" enchant="0"/>
   <ingredient id="26122" count="1" enchant="0"/>
   <ingredient id="28227" count="1" enchant="0"/>
   <ingredient id="28217" count="1" enchant="0"/>
   <ingredient id="28222" count="1" enchant="0"/>
 
   <production id="16501" count="1" enchant="0"/>
   <production id="16503" count="1" enchant="0"/>
   <production id="16505" count="1" enchant="0"/>
   <production id="16507" count="1" enchant="0"/>
   <production id="16509" count="1" enchant="0"/>    
   </item>
   </list>